<?xml version="1.0" encoding="euc-kr" ?>

<clientinfo>
	<desc>philippine AWS Server</desc>
	<servicetype>philippine</servicetype>
	<servertype>local</servertype>
	<hideaccountlist></hideaccountlist>
	<extendedslot></extendedslot>
	<readfolder></readfolder> 
	<connection>
		<display>MyServer</display>
		<desc>None</desc>
		<address>15.165.246.3</address>
		<port>6900</port>
		<version>1</version>
		<registrationweb>https://member.gnjoy.com.tw/signin.aspx</registrationweb>
		<aid>
			<admin>23769057</admin>
		</aid>
	</connection>
</clientinfo>

